recordbin/__init__.py
recordbin/__version__.py
recordbin/auth.py
recordbin/compat.py
recordbin/hooks.py
recordbin/recordbin.py
recordbin-0.1.1a1.dist-info/LICENSE
recordbin-0.1.1a1.dist-info/METADATA
recordbin-0.1.1a1.dist-info/WHEEL
recordbin-0.1.1a1.dist-info/top_level.txt
recordbin-0.1.1a1.dist-info/RECORD
