Metadata-Version: 2.1
Name: recordbin
Version: 0.1.1a1
Summary: Python API Client for RecordBin
Home-page: https://github.com/gtalarico/recordbin-python
Author: Gui Talarico
Author-email: gui.talarico+pip@gmail.com
License: The MIT License (MIT)
Keywords: recordbin,api,logger
Platform: UNKNOWN
Classifier: Development Status :: 4 - Beta
Classifier: Environment :: Console
Classifier: Intended Audience :: Developers
Classifier: Programming Language :: Python
Classifier: Topic :: Software Development
Classifier: Programming Language :: Python
Classifier: Programming Language :: Python :: 2.7
Classifier: Programming Language :: Python :: 3.4
Classifier: Programming Language :: Python :: 3.5
Classifier: Programming Language :: Python :: 3.6
Classifier: Programming Language :: Python :: Implementation :: CPython
Requires-Dist: requests (>=2.18.3)
